setup.cfg
setup.py
nimblenet/__init__.py
nimblenet/activation_functions.py
nimblenet/cost_functions.py
nimblenet/data_structures.py
nimblenet/evaluation_functions.py
nimblenet/neuralnet.py
nimblenet/preprocessing.py
nimblenet/tools.py
nimblenet.egg-info/PKG-INFO
nimblenet.egg-info/SOURCES.txt
nimblenet.egg-info/dependency_links.txt
nimblenet.egg-info/requires.txt
nimblenet.egg-info/top_level.txt
nimblenet/learning_algorithms/__init__.py
nimblenet/learning_algorithms/generalized_hebbian.py
nimblenet/learning_algorithms/resilient_backpropagation.py
nimblenet/learning_algorithms/scaled_conjugate_gradient.py
nimblenet/learning_algorithms/scipyoptimize.py
nimblenet/learning_algorithms/backpropagation/__init__.py
nimblenet/learning_algorithms/backpropagation/base.py
nimblenet/learning_algorithms/backpropagation/variations.py
nimblenet/learning_algorithms/commons/__init__.py
nimblenet/learning_algorithms/commons/utils.py