Metadata-Version: 1.1
Name: nimblenet
Version: 0.2.1
Summary: Efficient python (NumPy) neural network library.
Home-page: https://jorgenkg.github.io/python-neural-network/
Author: Jorgen Grimnes
Author-email: jorgenkg@yahoo.no
License: UNKNOWN
Download-URL: https://github.com/jorgenkg/python-neural-network/tarball/0.2.1
Keywords: python,numpy,neuralnetwork,neural,network,efficient,lightweight
Platform: UNKNOWN
Classifier: Programming Language :: Python :: 2.7
Classifier: Topic :: Scientific/Engineering :: Artificial Intelligence
